statcoderrb/__init__.py
statcoderrb/code1.py
statcoderrb/code2.py
statcoderrb/code3.py
statcoderrb/code4.py
statcoderrb/code5.py
statcoderrb/code6.py
statcoderrb/code7.py
statcoderrb/code8.py
statcoderrb-0.1.dist-info/LICENSE
statcoderrb-0.1.dist-info/METADATA
statcoderrb-0.1.dist-info/WHEEL
statcoderrb-0.1.dist-info/top_level.txt
statcoderrb-0.1.dist-info/RECORD
